logger/__init__.py
logger/admin.py
logger/apps.py
logger/middleware.py
logger/models.py
logger/signals.py
logger/tests.py
logger/urls.py
logger/views.py
django_logger_test-1.3.8.dist-info/METADATA
django_logger_test-1.3.8.dist-info/WHEEL
django_logger_test-1.3.8.dist-info/top_level.txt
django_logger_test-1.3.8.dist-info/RECORD
