Metadata-Version: 2.1
Name: django-logger-test
Version: 1.3.8
Summary: Sample installable django app
Home-page: https://m2dtech.com
License: FREE
Platform: UNKNOWN
Classifier: Topic :: Software Development :: Libraries :: Python Modules
Requires-Python: >=3.6
Requires-Dist: Django
Requires-Dist: django-simple-history
